ossbomer_oslc
